basic_controller/__init__.py
basic_controller/controller.py
BasicController-0.1.1568711170.dist-info/METADATA
BasicController-0.1.1568711170.dist-info/WHEEL
BasicController-0.1.1568711170.dist-info/top_level.txt
BasicController-0.1.1568711170.dist-info/RECORD
