Metadata-Version: 2.1
Name: BasicController
Version: 0.1.1568711170
Summary: basic controller template
Home-page: https://github.com/JulianKimmig/BasicController
Author: Julian Kimmig
Author-email: julian-kimmig@gmx.net
License: UNKNOWN
Platform: UNKNOWN
Classifier: Programming Language :: Python :: 3
Classifier: License :: OSI Approved :: MIT License
Classifier: Operating System :: OS Independent
